setup.cfg
setup.py
crazy/__init__.py
crazy/crazy_decrypter.py
crazy_decrypter.egg-info/PKG-INFO
crazy_decrypter.egg-info/SOURCES.txt
crazy_decrypter.egg-info/dependency_links.txt
crazy_decrypter.egg-info/top_level.txt