Metadata-Version: 1.1
Name: crazy-decrypter
Version: 0.0.3
Summary: Python Crazy Decrypter is real crazy tool to decrypt md5, sha1, sha224, sha256, sha384, and sha512 with Brute Force method.
Home-page: https://github.com/agusmakmun/Crazy-Decrypter/
Author: Agus Makmun (Summon Agus)
Author-email: ags@dracos-linux.id
License: MIT
Download-URL: https://github.com/agusmakmun/Crazy-Decrypter/tarball/v0.0.3
Keywords: Crazy Decrypter,Python Crazy Decrypter
Platform: UNKNOWN
